wren/__init__.py
wren/cli.py
wren/core.py
wren/http_server.py
wren/matrix.py
wren/telegram.py
wren_tools-0.5.0.dist-info/METADATA
wren_tools-0.5.0.dist-info/WHEEL
wren_tools-0.5.0.dist-info/entry_points.txt
wren_tools-0.5.0.dist-info/top_level.txt
wren_tools-0.5.0.dist-info/RECORD
