Metadata-Version: 2.4
Name: wren-tools
Version: 0.5.0
Summary: The simplest task management system with the most advanced features
Project-URL: Homepage, https://github.com/bjesus/wren
Keywords: note taking,todo,to do,task management
Classifier: License :: OSI Approved :: MIT License
Requires-Python: >=3.11
Requires-Dist: croniter==2.0.1
Requires-Dist: pathvalidate==3.2.0
Requires-Dist: platformdirs==4.1.0
Requires-Dist: python-dateutil==2.8.2
Requires-Dist: pytz==2023.3.post1
Provides-Extra: telegram
Requires-Dist: telebot==0.0.5; extra == "telegram"
Requires-Dist: tzlocal==5.2; extra == "telegram"
Requires-Dist: idna==3.6; extra == "telegram"
Requires-Dist: APScheduler==3.10.4; extra == "telegram"
Requires-Dist: pyTelegramBotAPI==4.14.1; extra == "telegram"
Requires-Dist: certifi==2023.11.17; extra == "telegram"
Requires-Dist: charset-normalizer==3.3.2; extra == "telegram"
Provides-Extra: http
Requires-Dist: bottle==0.12.25; extra == "http"
Provides-Extra: matrix
Requires-Dist: APScheduler==3.10.4; extra == "matrix"
Requires-Dist: simplematrixbotlib==2.10.3; extra == "matrix"
Provides-Extra: llm
Requires-Dist: litellm==1.66.3; extra == "llm"
